{
	"faqList" : {
		"mainTitle" : "FAQ",
		"allControl" : false,
		"faqContList" : [
			{
				"type" : "html",
				"que" : "청약철회 후 보험료 반송은 언제 이루어 지나요? 언제줄건가요? 언제줄건가요? 언제줄건가요? 언제줄건가요? 언제줄건가요? 언제줄건가요? 언제줄건가요? 언제줄건가요?",
				"innerdata" : "/common/basic-component/html-comp/html-inner/table/form-lib-table1"
			},
			{
				"type" : "html",
				"que" : "청약철회 후 보험료 반송은 언제 이루어 지나요? 언제줄건가요? 언제줄건가요? 언제줄건가요? 언제줄건가요? 언제줄건가요? 언제줄건가요? 언제줄건가요? 언제줄건가요?",
				"innerdata" : "/common/basic-component/html-comp/html-inner/accordion/faq-accordion1"
			},
			{
				"que" : "청약철회 후 보험료 반송은 언제 이루어 지나요?",
				"anw" : "해외로 출국하시더라도 계속적으로 보험료 납입을 하시면 보험계약의 유지가 가능하며, 사고 시 국내에서 보험금 청구를 통하여 보장받으실 수 있습니다."
			},
			{
				"que" : "청약철회 후 보험료 반송은 언제 이루어 지나요?",
				"anw" : "해외로 출국하시더라도 계속적으로 보험료 납입을 하시면 보험계약의 유지가 가능하며, 사고 시 국내에서 보험금 청구를 통하여 보장받으실 수 있습니다."
			}
		]
	}

}